testcontainers/oracle/__init__.py
tests/test_oracle.py
testcontainers_oracle-0.0.1rc1.dist-info/METADATA
testcontainers_oracle-0.0.1rc1.dist-info/WHEEL
testcontainers_oracle-0.0.1rc1.dist-info/top_level.txt
testcontainers_oracle-0.0.1rc1.dist-info/RECORD
